shlnb/__init__.py
shlnb/shlnb.py
shlnb-0.0.4.dist-info/LICENSE
shlnb-0.0.4.dist-info/METADATA
shlnb-0.0.4.dist-info/WHEEL
shlnb-0.0.4.dist-info/top_level.txt
shlnb-0.0.4.dist-info/RECORD
