Metadata-Version: 2.1
Name: shlnb
Version: 0.0.4
Summary: Beamforming and signal analysis of microphone ULA
Home-page: https://github.com/butterlyn/SHLNB
Author: Nicholas Butterly
Author-email: butterlyn888@gmail.com
License: UNKNOWN
Platform: UNKNOWN
Classifier: Programming Language :: Python :: 3
Classifier: License :: OSI Approved :: MIT License
Classifier: Operating System :: OS Independent
Requires-Python: >=3.6
Requires-Dist: arlpy
Requires-Dist: numpy (>=1.11.3)
Requires-Dist: setuptools
Requires-Dist: soundfile
